HuibianyuyanRumenjiaochengCYuyanBianchengWangFix1/README.md
HuibianyuyanRumenjiaochengCYuyanBianchengWangFix1/__init__.py
HuibianyuyanRumenjiaochengCYuyanBianchengWangFix1/__main__.py
HuibianyuyanRumenjiaochengCYuyanBianchengWangFix1/file.epub
HuibianyuyanRumenjiaochengCYuyanBianchengWangFix1/index.html
HuibianyuyanRumenjiaochengCYuyanBianchengWangFix1/css/__init__.py
HuibianyuyanRumenjiaochengCYuyanBianchengWangFix1/css/annotations.css
HuibianyuyanRumenjiaochengCYuyanBianchengWangFix1/css/main.css
HuibianyuyanRumenjiaochengCYuyanBianchengWangFix1/css/normalize.css
HuibianyuyanRumenjiaochengCYuyanBianchengWangFix1/css/popup.css
HuibianyuyanRumenjiaochengCYuyanBianchengWangFix1/font/__init__.py
HuibianyuyanRumenjiaochengCYuyanBianchengWangFix1/font/fontello.eot
HuibianyuyanRumenjiaochengCYuyanBianchengWangFix1/font/fontello.svg
HuibianyuyanRumenjiaochengCYuyanBianchengWangFix1/font/fontello.ttf
HuibianyuyanRumenjiaochengCYuyanBianchengWangFix1/font/fontello.woff
HuibianyuyanRumenjiaochengCYuyanBianchengWangFix1/img/__init__.py
HuibianyuyanRumenjiaochengCYuyanBianchengWangFix1/img/annotator-glyph-sprite.png
HuibianyuyanRumenjiaochengCYuyanBianchengWangFix1/img/annotator-icon-sprite.png
HuibianyuyanRumenjiaochengCYuyanBianchengWangFix1/img/apple-touch-icon.png
HuibianyuyanRumenjiaochengCYuyanBianchengWangFix1/img/cancelfullscreen.png
HuibianyuyanRumenjiaochengCYuyanBianchengWangFix1/img/close.png
HuibianyuyanRumenjiaochengCYuyanBianchengWangFix1/img/fullscreen.png
HuibianyuyanRumenjiaochengCYuyanBianchengWangFix1/img/loader.gif
HuibianyuyanRumenjiaochengCYuyanBianchengWangFix1/img/menu-icon.png
HuibianyuyanRumenjiaochengCYuyanBianchengWangFix1/img/save.png
HuibianyuyanRumenjiaochengCYuyanBianchengWangFix1/img/saved.png
HuibianyuyanRumenjiaochengCYuyanBianchengWangFix1/img/settings-s.png
HuibianyuyanRumenjiaochengCYuyanBianchengWangFix1/img/settings.png
HuibianyuyanRumenjiaochengCYuyanBianchengWangFix1/img/star.png
huibianyuyan_rumenjiaocheng_c_yuyan_biancheng_wang_fix1-2025.3.24.0.dist-info/METADATA
huibianyuyan_rumenjiaocheng_c_yuyan_biancheng_wang_fix1-2025.3.24.0.dist-info/WHEEL
huibianyuyan_rumenjiaocheng_c_yuyan_biancheng_wang_fix1-2025.3.24.0.dist-info/entry_points.txt
huibianyuyan_rumenjiaocheng_c_yuyan_biancheng_wang_fix1-2025.3.24.0.dist-info/top_level.txt
huibianyuyan_rumenjiaocheng_c_yuyan_biancheng_wang_fix1-2025.3.24.0.dist-info/RECORD
